abortion_policies/Gestational Limits/HTML/Gestational Limits.html
abortion_policies/Gestational Limits/JSON/Gestational Limits.json
abortion_policies/Gestational Limits/MP3/Alabama Gestational Limits.mp3
abortion_policies/Gestational Limits/MP3/Arizona Gestational Limits.mp3
abortion_policies/Gestational Limits/MP3/Arkansas Gestational Limits.mp3
abortion_policies/Gestational Limits/MP3/California Gestational Limits.mp3
abortion_policies/Gestational Limits/MP3/Connecticut Gestational Limits.mp3
abortion_policies/Gestational Limits/MP3/Delaware Gestational Limits.mp3
abortion_policies/Gestational Limits/MP3/District of Columbia Gestational Limits.mp3
abortion_policies/Gestational Limits/MP3/Florida Gestational Limits.mp3
abortion_policies/Gestational Limits/MP3/Georgia Gestational Limits.mp3
abortion_policies/Gestational Limits/MP3/Hawaii Gestational Limits.mp3
abortion_policies/Gestational Limits/MP3/Idaho Gestational Limits.mp3
abortion_policies/Gestational Limits/MP3/Illinois Gestational Limits.mp3
abortion_policies/Gestational Limits/MP3/Indiana Gestational Limits.mp3
abortion_policies/Gestational Limits/MP3/Iowa Gestational Limits.mp3
abortion_policies/Gestational Limits/MP3/Kansas Gestational Limits.mp3
abortion_policies/Gestational Limits/MP3/Kentucky Gestational Limits.mp3
abortion_policies/Gestational Limits/MP3/Louisiana Gestational Limits.mp3
abortion_policies/Gestational Limits/MP3/Maine Gestational Limits.mp3
abortion_policies/Gestational Limits/MP3/Maryland Gestational Limits.mp3
abortion_policies/Gestational Limits/MP3/Massachusetts Gestational Limits.mp3
abortion_policies/Gestational Limits/MP3/Michigan Gestational Limits.mp3
abortion_policies/Gestational Limits/MP3/Minnesota Gestational Limits.mp3
abortion_policies/Gestational Limits/MP3/Mississippi Gestational Limits.mp3
abortion_policies/Gestational Limits/MP3/Missouri Gestational Limits.mp3
abortion_policies/Gestational Limits/MP3/Montana Gestational Limits.mp3
abortion_policies-1.0.0.dist-info/entry_points.txt
abortion_policies-1.0.0.dist-info/LICENSE
abortion_policies-1.0.0.dist-info/WHEEL
abortion_policies-1.0.0.dist-info/METADATA
abortion_policies-1.0.0.dist-info/RECORD
